Workbook

Sheet 使い方
A1: KONCOCHII 損益分岐点シミュレーション（詳細版）
A3: このブックは前提を変えると全タブが自動再計算します。黄色セル＝入力、黒字＝計算結果です。
A5: 【タブ構成】
A6: 1) ダッシュボード … 主要な結果（月次損益・黒字化ライン・黒字化月・最大必要資金）を一覧。まずここを見る。
A7: 2) 収益・原価 … サイズ(S/M/L)×プラン(3/6/12h)の構成比と、直販/ホテル紹介/OTAのチャネル構成から、1予約の加重単価・純貢献を算出。
A8: 3) 固定費 … 人員×人数×月給＋インフラ。人を増減すると即反映。
A9: 4) 24ヶ月キャッシュフロー … 店舗展開スケジュールと立ち上がり(ランプ)から、月次損益と累計現金、黒字化月・最大必要運転資金を算出。
A10: 5) 感度分析 … 2つの前提を振ったときの月次損益グリッド（赤=赤字/緑=黒字）。
A12: 【使い方の順序】
A13: ① 収益・原価タブでサイズ/プラン/チャネル構成と単価を現実に合わせる → 1予約あたり純貢献が決まる。
A14: ② 固定費タブで人員と月額を入れる。 ③ ダッシュボードで店舗数・件数/日を動かし損益と分岐点を見る。
A15: ④ 24ヶ月タブで展開スケジュールを入れ、黒字化月と最大必要資金（資金調達額の目安）を確認。
... A18: 為替 約26,300 VND/USD（2026-07・参考）。

Sheet ダッシュボード
A1: ダッシュボード（主要結果）
A2: 黄色=入力。前提の詳細は「収益・原価」「固定費」タブ。ここでは規模（店舗数・件数）を動かす。
A4: 規模の入力 | D4: 1予約あたり（収益・原価タブより）
A5: 店舗数 | B5: 3 | D5: 平均客単価 ARPB | E5: =収益・原価!B20 -> 109850
A6: 1店舗あたり予約/日 | B6: 7 | D6: 純貢献額 /予約 | E6: =収益・原価!B39 -> 39546
A7: 営業日/月 | B7: 30 | D7: 純貢献率 | E7: =収益・原価!B39/収益・原価!B20 -> 0.36
A8: 為替 VND/USD | B8: 26300
A10: 月次 損益（現在の規模） | D10: 損益分岐（黒字化ライン）
A11: 月間予約数 | B11: =B5*B6*B7 -> 630 | D11: 損益分岐 月間予約数 | E11: =IF(収益・原価!B39<=0,"貢献≤0",CEILING(固定費!D20/収益・原価!B39,1)) -> 2150
A12: 月間売上 | B12: =B11*収益・原価!B20 -> 69205500 | D12: 損益分岐 店舗数（現在の件数/日） | E12: =IF(収益・原価!B39<=0,"—",CEILING(固定費!D20/(収益・原価!B39*B6*B7),1)) -> 11
A13: 月間純貢献 | B13: =B11*収益・原価!B39 -> 24913980 | D13: 損益分岐 件数/日（現在の店舗数） | E13: =IF(収益・原価!B39<=0,"—",CEILING(固定費!D20/(収益・原価!B39*B5*B7),0.1)) -> 23.9
A14: 固定費/月 | B14: =固定費!D20 -> 85000000 | D14: 現在の黒字/赤字判定 | E14: =IF(B15>=0,"黒字","赤字") -> 赤字
A15: 月次損益 | B15: =B13-固定費!D20 -> -60086020 | D15: 黒字化まで不足 予約数/月 | E15: =MAX(0,IF(収益・原価!B39<=0,0,CEILING(固定費!D20/収益・原価!B39,1)-B11)) -> 1520
A16: 月次損益（USD参考） | B16: =B15/B8 -> -2284.6395
A17: 粗利率でみた損益（月次損益/売上） | B17: =IF(B12=0,0,B15/B12) -> -0.86822608

Sheet 収益・原価
A1: 収益・原価モデル（1予約あたりの単価と純貢献を算出）
A2: 黄色=入力。価格はprice_plans（千₫）。構成比の各合計は100%になるよう入力。
A4: ① 価格表（price_plans・₫／1個）
A5: サイズ ＼ プラン | B5: 3h | C5: 6h | D5: 12h
A6: S | B6: 50000 | C6: 70000 | D6: 100000
A7: M | B7: 70000 | C7: 100000 | D7: 150000
A8: L | B8: 100000 | C8: 150000 | D8: 200000
A10: ② サイズ構成比（合計100%） | D10: ③ プラン構成比（合計100%）
A11: サイズ | B11: 構成比 | D11: プラン | E11: 構成比
A12: S | B12: 0.5 | D12: 3h | E12: 0.5
A13: M | B13: 0.35 | D13: 6h | E13: 0.35
A14: L | B14: 0.15 | D14: 12h | E14: 0.15
A15: 合計 | B15: =SUM(B12:B14) -> 1 | D15: 合計 | E15: =SUM(E12:E14) -> 1
A17: ④ 加重平均（自動計算）
A18: 加重平均単価 /個（サイズ×プラン） | B18: =B12*(E12*B6+E13*C6+E14*D6)+B13*(E12*B7+E13*C7+E14*D7)+B14*(E12*B8+E13*C8+E14*D8) -> 84500
A19: 平均 個数/予約 | B19: 1.3
A20: 平均客単価 ARPB /予約（=加重単価×個数） | B20: =B18*B19 -> 109850
A22: ⑤ 変動原価（対売上）
A23: 店舗委託料 | B23: 0.4
A24: 決済手数料 | B24: 0.03
A25: 保険料 | B25: 0.06
A26: システム配賦 | B26: 0.05
A27: 控除合計率 | B27: =SUM(B23:B26) -> 0.54
A28: 粗貢献率（1−控除） | B28: =1-B27 -> 0.46
A30: ⑥ チャネル構成と集客手数料
A31: チャネル | B31: 構成比 | C31: 集客手数料率 | D31: 加重手数料
A32: 直販（自然流入/SEO） | B32: 0.45 | C32: 0 | D32: =B32*C32 -> 0
A33: ホテル/バス紹介(B2B2C) | B33: 0.25 | C33: 0.1 | D33: =B33*C33 -> 0.025
A34: OTA(Klook/KKday) | B34: 0.3 | C34: 0.25 | D34: =B34*C34 -> 0.075
A35: 合計 / 加重集客手数料率 | B35: =SUM(B32:B34) -> 1 | D35: =SUM(D32:D34) -> 0.1
A36: ⑦ 1予約あたり純貢献（最終）
A37: 粗貢献額 /予約（ARPB×粗貢献率） | B37: =B20*B28 -> 50531
A38: 集客手数料 /予約（ARPB×加重手数料率） | B38: =B20*D35 -> 10985
A39: 純貢献額 /予約 | B39: =B37-B38 -> 39546
A40: 純貢献率（対ARPB） | B40: =B39/B20 -> 0.36

Sheet 固定費
A1: 月次固定費（人員×月給＋インフラ）
A2: 黄色=入力。人数と月給を変えると小計・合計が再計算されます。
A4: 人件費
A5: 役割 | B5: 人数 | C5: 月給/人(₫) | D5: 小計/月(₫) | E5: 備考
A6: 多言語CS | B6: 2 | C6: 12000000 | D6: =B6*C6 -> 24000000 | E6: 日英越＋(韓/中)。即応対応
A7: 店舗管理・営業 | B7: 1 | C7: 18000000 | D7: =B7*C7 -> 18000000 | E7: 巡回・研修・新規開拓
A8: オペ/精算・保険事務 | B8: 1 | C8: 13000000 | D8: =B8*C8 -> 13000000 | E8: 精算突合・クレーム・保険請求
A9: マネージャー/PM | B9: 1 | C9: 20000000 | D9: =B9*C9 -> 20000000 | E9: 兼任可ならPoCは0.5でも可
A10: 人件費 小計/月 | D10: =SUM(D6:D9) -> 75000000
A12: インフラ・その他
A13: 項目 | D13: 月額(₫) | E13: 備考
A14: システム/インフラ(Supabase/Vercel/ドメイン) | D14: 3000000 | E14: 利用量で増減
A15: 2C2P固定費・通信 | D15: 2000000 | E15: 決済の月額固定分
A16: 会計/税務・その他 | D16: 3000000 | E16: 記帳・雑費
A17: マーケ固定(SEO/素材) | D17: 2000000 | E17: 広告変動費はチャネル側で計上
A18: インフラ小計/月 | D18: =SUM(D14:D17) -> 10000000
A20: 固定費合計 /月 | D20: =D10+D18 -> 85000000
A22: 一時費用（初期・参考／損益分岐には非算入）
A23: 初期開発・セットアップ | D23: 0 | E23: AI開発で圧縮想定。実額を入れる
A24: 店舗什器/タグ/研修 初期 | D24: 15000000
A25: 保証金/契約一時金 | D25: 0
A26: 一時費用 合計 | D26: =SUM(D23:D25) -> 15000000

Sheet 24ヶ月キャッシュフロー
A1: 24ヶ月 キャッシュフロー（展開スケジュール→黒字化月・必要資金）
A2: 黄色=入力（店舗数・件数/日の推移）。営業日/月と純貢献/固定費は他タブ連動。固定費は当面フラット前提（拡大時は固定費タブで増員）。
A4: 月 | B4: 稼働店舗 | C4: 件数/日·店 | D4: 月間予約 | E4: 月間売上 | F4: 月間純貢献 | G4: 固定費 | H4: 月次損益 | I4: 累計現金 | L4: 黒字月? | M4: 現金+月?
A5: 1 | B5: 3 | C5: 4 | D5: =B5*C5*ダッシュボード!B7 -> 360 | E5: =D5*収益・原価!B20 -> 39546000 | F5: =D5*収益・原価!B39 -> 14236560 | G5: =固定費!D20 -> 85000000 | H5: =F5-G5 -> -70763440 | I5: =H5-固定費!D26 -> -85763440 | L5: =IF(H5>=0,A5,9999) -> 9999 | M5: =IF(I5>=0,A5,9999) -> 9999
A6: 2 | B6: 3 | C6: 4.5 | D6: =B6*C6*ダッシュボード!B7 -> 405 | E6: =D6*収益・原価!B20 -> 44489250 | F6: =D6*収益・原価!B39 -> 16016130 | G6: =固定費!D20 -> 85000000 | H6: =F6-G6 -> -68983870 | I6: =I5+H6 -> -154747310 | L6: =IF(H6>=0,A6,9999) -> 9999 | M6: =IF(I6>=0,A6,9999) -> 9999
A7: 3 | B7: 3 | C7: 5 | D7: =B7*C7*ダッシュボード!B7 -> 450 | E7: =D7*収益・原価!B20 -> 49432500 | F7: =D7*収益・原価!B39 -> 17795700 | G7: =固定費!D20 -> 85000000 | H7: =F7-G7 -> -67204300 | I7: =I6+H7 -> -221951610 | L7: =IF(H7>=0,A7,9999) -> 9999 | M7: =IF(I7>=0,A7,9999) -> 9999
A8: 4 | B8: 5 | C8: 5.5 | D8: =B8*C8*ダッシュボード!B7 -> 825 | E8: =D8*収益・原価!B20 -> 90626250 | F8: =D8*収益・原価!B39 -> 32625450 | G8: =固定費!D20 -> 85000000 | H8: =F8-G8 -> -52374550 | I8: =I7+H8 -> -274326160 | L8: =IF(H8>=0,A8,9999) -> 9999 | M8: =IF(I8>=0,A8,9999) -> 9999
A9: 5 | B9: 5 | C9: 6 | D9: =B9*C9*ダッシュボード!B7 -> 900 | E9: =D9*収益・原価!B20 -> 98865000 | F9: =D9*収益・原価!B39 -> 35591400 | G9: =固定費!D20 -> 85000000 | H9: =F9-G9 -> -49408600 | I9: =I8+H9 -> -323734760 | L9: =IF(H9>=0,A9,9999) -> 9999 | M9: =IF(I9>=0,A9,9999) -> 9999
A10: 6 | B10: 5 | C10: 6.5 | D10: =B10*C10*ダッシュボード!B7 -> 975 | E10: =D10*収益・原価!B20 -> 107103750 | F10: =D10*収益・原価!B39 -> 38557350 | G10: =固定費!D20 -> 85000000 | H10: =F10-G10 -> -46442650 | I10: =I9+H10 -> -370177410 | L10: =IF(H10>=0,A10,9999) -> 9999 | M10: =IF(I10>=0,A10,9999) -> 9999
A11: 7 | B11: 8 | C11: 7 | D11: =B11*C11*ダッシュボード!B7 -> 1680 | E11: =D11*収益・原価!B20 -> 184548000 | F11: =D11*収益・原価!B39 -> 66437280 | G11: =固定費!D20 -> 85000000 | H11: =F11-G11 -> -18562720 | I11: =I10+H11 -> -388740130 | L11: =IF(H11>=0,A11,9999) -> 9999 | M11: =IF(I11>=0,A11,9999) -> 9999
A12: 8 | B12: 8 | C12: 7.5 | D12: =B12*C12*ダッシュボード!B7 -> 1800 | E12: =D12*収益・原価!B20 -> 197730000 | F12: =D12*収益・原価!B39 -> 71182800 | G12: =固定費!D20 -> 85000000 | H12: =F12-G12 -> -13817200 | I12: =I11+H12 -> -402557330 | L12: =IF(H12>=0,A12,9999) -> 9999 | M12: =IF(I12>=0,A12,9999) -> 9999
A13: 9 | B13: 8 | C13: 8 | D13: =B13*C13*ダッシュボード!B7 -> 1920 | E13: =D13*収益・原価!B20 -> 210912000 | F13: =D13*収益・原価!B39 -> 75928320 | G13: =固定費!D20 -> 85000000 | H13: =F13-G13 -> -9071680 | I13: =I12+H13 -> -411629010 | L13: =IF(H13>=0,A13,9999) -> 9999 | M13: =IF(I13>=0,A13,9999) -> 9999
A14: 10 | B14: 8 | C14: 8.5 | D14: =B14*C14*ダッシュボード!B7 -> 2040 | E14: =D14*収益・原価!B20 -> 224094000 | F14: =D14*収益・原価!B39 -> 80673840 | G14: =固定費!D20 -> 85000000 | H14: =F14-G14 -> -4326160 | I14: =I13+H14 -> -415955170 | L14: =IF(H14>=0,A14,9999) -> 9999 | M14: =IF(I14>=0,A14,9999) -> 9999
A15: 11 | B15: 8 | C15: 9 | D15: =B15*C15*ダッシュボード!B7 -> 2160 | E15: =D15*収益・原価!B20 -> 237276000 | F15: =D15*収益・原価!B39 -> 85419360 | G15: =固定費!D20 -> 85000000 | H15: =F15-G15 -> 419360 | I15: =I14+H15 -> -415535810 | L15: =IF(H15>=0,A15,9999) -> 11 | M15: =IF(I15>=0,A15,9999) -> 9999
A16: 12 | B16: 8 | C16: 9.5 | D16: =B16*C16*ダッシュボード!B7 -> 2280 | E16: =D16*収益・原価!B20 -> 250458000 | F16: =D16*収益・原価!B39 -> 90164880 | G16: =固定費!D20 -> 85000000 | H16: =F16-G16 -> 5164880 | I16: =I15+H16 -> -410370930 | L16: =IF(H16>=0,A16,9999) -> 12 | M16: =IF(I16>=0,A16,9999) -> 9999
A17: 13 | B17: 12 | C17: 10 | D17: =B17*C17*ダッシュボード!B7 -> 3600 | E17: =D17*収益・原価!B20 -> 395460000 | F17: =D17*収益・原価!B39 -> 142365600 | G17: =固定費!D20 -> 85000000 | H17: =F17-G17 -> 57365600 | I17: =I16+H17 -> -353005330 | L17: =IF(H17>=0,A17,9999) -> 13 | M17: =IF(I17>=0,A17,9999) -> 9999
A18: 14 | B18: 12 | C18: 10 | D18: =B18*C18*ダッシュボード!B7 -> 3600 | E18: =D18*収益・原価!B20 -> 395460000 | F18: =D18*収益・原価!B39 -> 142365600 | G18: =固定費!D20 -> 85000000 | H18: =F18-G18 -> 57365600 | I18: =I17+H18 -> -295639730 | L18: =IF(H18>=0,A18,9999) -> 14 | M18: =IF(I18>=0,A18,9999) -> 9999
A19: 15 | B19: 12 | C19: 10 | D19: =B19*C19*ダッシュボード!B7 -> 3600 | E19: =D19*収益・原価!B20 -> 395460000 | F19: =D19*収益・原価!B39 -> 142365600 | G19: =固定費!D20 -> 85000000 | H19: =F19-G19 -> 57365600 | I19: =I18+H19 -> -238274130 | L19: =IF(H19>=0,A19,9999) -> 15 | M19: =IF(I19>=0,A19,9999) -> 9999
A20: 16 | B20: 12 | C20: 10 | D20: =B20*C20*ダッシュボード!B7 -> 3600 | E20: =D20*収益・原価!B20 -> 395460000 | F20: =D20*収益・原価!B39 -> 142365600 | G20: =固定費!D20 -> 85000000 | H20: =F20-G20 -> 57365600 | I20: =I19+H20 -> -180908530 | L20: =IF(H20>=0,A20,9999) -> 16 | M20: =IF(I20>=0,A20,9999) -> 9999
A21: 17 | B21: 12 | C21: 10 | D21: =B21*C21*ダッシュボード!B7 -> 3600 | E21: =D21*収益・原価!B20 -> 395460000 | F21: =D21*収益・原価!B39 -> 142365600 | G21: =固定費!D20 -> 85000000 | H21: =F21-G21 -> 57365600 | I21: =I20+H21 -> -123542930 | L21: =IF(H21>=0,A21,9999) -> 17 | M21: =IF(I21>=0,A21,9999) -> 9999
A22: 18 | B22: 12 | C22: 10 | D22: =B22*C22*ダッシュボード!B7 -> 3600 | E22: =D22*収益・原価!B20 -> 395460000 | F22: =D22*収益・原価!B39 -> 142365600 | G22: =固定費!D20 -> 85000000 | H22: =F22-G22 -> 57365600 | I22: =I21+H22 -> -66177330 | L22: =IF(H22>=0,A22,9999) -> 18 | M22: =IF(I22>=0,A22,9999) -> 9999
A23: 19 | B23: 20 | C23: 10 | D23: =B23*C23*ダッシュボード!B7 -> 6000 | E23: =D23*収益・原価!B20 -> 659100000 | F23: =D23*収益・原価!B39 -> 237276000 | G23: =固定費!D20 -> 85000000 | H23: =F23-G23 -> 152276000 | I23: =I22+H23 -> 86098670 | L23: =IF(H23>=0,A23,9999) -> 19 | M23: =IF(I23>=0,A23,9999) -> 19
A24: 20 | B24: 20 | C24: 10 | D24: =B24*C24*ダッシュボード!B7 -> 6000 | E24: =D24*収益・原価!B20 -> 659100000 | F24: =D24*収益・原価!B39 -> 237276000 | G24: =固定費!D20 -> 85000000 | H24: =F24-G24 -> 152276000 | I24: =I23+H24 -> 238374670 | L24: =IF(H24>=0,A24,9999) -> 20 | M24: =IF(I24>=0,A24,9999) -> 20
A25: 21 | B25: 20 | C25: 10 | D25: =B25*C25*ダッシュボード!B7 -> 6000 | E25: =D25*収益・原価!B20 -> 659100000 | F25: =D25*収益・原価!B39 -> 237276000 | G25: =固定費!D20 -> 85000000 | H25: =F25-G25 -> 152276000 | I25: =I24+H25 -> 390650670 | L25: =IF(H25>=0,A25,9999) -> 21 | M25: =IF(I25>=0,A25,9999) -> 21
A26: 22 | B26: 20 | C26: 10 | D26: =B26*C26*ダッシュボード!B7 -> 6000 | E26: =D26*収益・原価!B20 -> 659100000 | F26: =D26*収益・原価!B39 -> 237276000 | G26: =固定費!D20 -> 85000000 | H26: =F26-G26 -> 152276000 | I26: =I25+H26 -> 542926670 | L26: =IF(H26>=0,A26,9999) -> 22 | M26: =IF(I26>=0,A26,9999) -> 22
A27: 23 | B27: 20 | C27: 10 | D27: =B27*C27*ダッシュボード!B7 -> 6000 | E27: =D27*収益・原価!B20 -> 659100000 | F27: =D27*収益・原価!B39 -> 237276000 | G27: =固定費!D20 -> 85000000 | H27: =F27-G27 -> 152276000 | I27: =I26+H27 -> 695202670 | L27: =IF(H27>=0,A27,9999) -> 23 | M27: =IF(I27>=0,A27,9999) -> 23
A28: 24 | B28: 20 | C28: 10 | D28: =B28*C28*ダッシュボード!B7 -> 6000 | E28: =D28*収益・原価!B20 -> 659100000 | F28: =D28*収益・原価!B39 -> 237276000 | G28: =固定費!D20 -> 85000000 | H28: =F28-G28 -> 152276000 | I28: =I27+H28 -> 847478670 | L28: =IF(H28>=0,A28,9999) -> 24 | M28: =IF(I28>=0,A28,9999) -> 24
A30: サマリー
A31: 営業黒字化 月（月次損益が初めて≥0） | C31: =IF(MIN(L5:L28)=9999,"未達",MIN(L5:L28)) -> 11
A32: 累計現金プラス転換 月 | C32: =IF(MIN(M5:M28)=9999,"未達",MIN(M5:M28)) -> 19
A33: 最大必要運転資金（累計現金の最深マイナス） | C33: =MAX(0,-MIN(I5:I28)) -> 415955170
A34: 24ヶ月末 累計現金 | C34: =I28 -> 847478670
A35: 24ヶ月末 稼働店舗 / 月次損益 | C35: =B28 -> 20 | D35: =H28 -> 152276000
A36: 注：固定費フラット前提。拡大に伴うCS/巡回増員は固定費タブで反映を。

Sheet 感度分析
A1: 感度分析（月次損益 ₫）
A2: 前提（純貢献額/予約・固定費・営業日）は他タブ連動。赤=赤字/緑=黒字。
A4: 表1: 店舗数（列）× 件数/日（行）
A5: 件数/日 ＼ 店舗数 | B5: 3 | C5: 5 | D5: 8 | E5: 10 | F5: 15 | G5: 20
A6: 4 | B6: =3*4*ダッシュボード!B7*収益・原価!B39-固定費!D20 -> -70763440 | C6: =5*4*ダッシュボード!B7*収益・原価!B39-固定費!D20 -> -61272400 | D6: =8*4*ダッシュボード!B7*収益・原価!B39-固定費!D20 -> -47035840 | E6: =10*4*ダッシュボード!B7*収益・原価!B39-固定費!D20 -> -37544800 | F6: =15*4*ダッシュボード!B7*収益・原価!B39-固定費!D20 -> -13817200 | G6: =20*4*ダッシュボード!B7*収益・原価!B39-固定費!D20 -> 9910400
A7: 5 | B7: =3*5*ダッシュボード!B7*収益・原価!B39-固定費!D20 -> -67204300 | C7: =5*5*ダッシュボード!B7*収益・原価!B39-固定費!D20 -> -55340500 | D7: =8*5*ダッシュボード!B7*収益・原価!B39-固定費!D20 -> -37544800 | E7: =10*5*ダッシュボード!B7*収益・原価!B39-固定費!D20 -> -25681000 | F7: =15*5*ダッシュボード!B7*収益・原価!B39-固定費!D20 -> 3978500 | G7: =20*5*ダッシュボード!B7*収益・原価!B39-固定費!D20 -> 33638000
A8: 6 | B8: =3*6*ダッシュボード!B7*収益・原価!B39-固定費!D20 -> -63645160 | C8: =5*6*ダッシュボード!B7*収益・原価!B39-固定費!D20 -> -49408600 | D8: =8*6*ダッシュボード!B7*収益・原価!B39-固定費!D20 -> -28053760 | E8: =10*6*ダッシュボード!B7*収益・原価!B39-固定費!D20 -> -13817200 | F8: =15*6*ダッシュボード!B7*収益・原価!B39-固定費!D20 -> 21774200 | G8: =20*6*ダッシュボード!B7*収益・原価!B39-固定費!D20 -> 57365600
A9: 7 | B9: =3*7*ダッシュボード!B7*収益・原価!B39-固定費!D20 -> -60086020 | C9: =5*7*ダッシュボード!B7*収益・原価!B39-固定費!D20 -> -43476700 | D9: =8*7*ダッシュボード!B7*収益・原価!B39-固定費!D20 -> -18562720 | E9: =10*7*ダッシュボード!B7*収益・原価!B39-固定費!D20 -> -1953400 | F9: =15*7*ダッシュボード!B7*収益・原価!B39-固定費!D20 -> 39569900 | G9: =20*7*ダッシュボード!B7*収益・原価!B39-固定費!D20 -> 81093200
A10: 8 | B10: =3*8*ダッシュボード!B7*収益・原価!B39-固定費!D20 -> -56526880 | C10: =5*8*ダッシュボード!B7*収益・原価!B39-固定費!D20 -> -37544800 | D10: =8*8*ダッシュボード!B7*収益・原価!B39-固定費!D20 -> -9071680 | E10: =10*8*ダッシュボード!B7*収益・原価!B39-固定費!D20 -> 9910400 | F10: =15*8*ダッシュボード!B7*収益・原価!B39-固定費!D20 -> 57365600 | G10: =20*8*ダッシュボード!B7*収益・原価!B39-固定費!D20 -> 104820800
A11: 9 | B11: =3*9*ダッシュボード!B7*収益・原価!B39-固定費!D20 -> -52967740 | C11: =5*9*ダッシュボード!B7*収益・原価!B39-固定費!D20 -> -31612900 | D11: =8*9*ダッシュボード!B7*収益・原価!B39-固定費!D20 -> 419360 | E11: =10*9*ダッシュボード!B7*収益・原価!B39-固定費!D20 -> 21774200 | F11: =15*9*ダッシュボード!B7*収益・原価!B39-固定費!D20 -> 75161300 | G11: =20*9*ダッシュボード!B7*収益・原価!B39-固定費!D20 -> 128548400
A12: 10 | B12: =3*10*ダッシュボード!B7*収益・原価!B39-固定費!D20 -> -49408600 | C12: =5*10*ダッシュボード!B7*収益・原価!B39-固定費!D20 -> -25681000 | D12: =8*10*ダッシュボード!B7*収益・原価!B39-固定費!D20 -> 9910400 | E12: =10*10*ダッシュボード!B7*収益・原価!B39-固定費!D20 -> 33638000 | F12: =15*10*ダッシュボード!B7*収益・原価!B39-固定費!D20 -> 92957000 | G12: =20*10*ダッシュボード!B7*収益・原価!B39-固定費!D20 -> 152276000
A14: 表2: 平均客単価（列）× 固定費倍率（行） ※現在の店舗数×件数/日で
A15: 固定費倍率 ＼ 客単価 | B15: 50000 | C15: 60000 | D15: 70000 | E15: 80000 | F15: 90000 | G15: 100000
A16: 0.75 | B16: =ダッシュボード!B5*ダッシュボード!B6*ダッシュボード!B7*(50000*(収益・原価!B39/収益・原価!B20))-固定費!D20*0.75 -> -52410000 | C16: =ダッシュボード!B5*ダッシュボード!B6*ダッシュボード!B7*(60000*(収益・原価!B39/収益・原価!B20))-固定費!D20*0.75 -> -50142000 | D16: =ダッシュボード!B5*ダッシュボード!B6*ダッシュボード!B7*(70000*(収益・原価!B39/収益・原価!B20))-固定費!D20*0.75 -> -47874000 | E16: =ダッシュボード!B5*ダッシュボード!B6*ダッシュボード!B7*(80000*(収益・原価!B39/収益・原価!B20))-固定費!D20*0.75 -> -45606000 | F16: =ダッシュボード!B5*ダッシュボード!B6*ダッシュボード!B7*(90000*(収益・原価!B39/収益・原価!B20))-固定費!D20*0.75 -> -43338000 | G16: =ダッシュボード!B5*ダッシュボード!B6*ダッシュボード!B7*(100000*(収益・原価!B39/収益・原価!B20))-固定費!D20*0.75 -> -41070000
A17: 1 | B17: =ダッシュボード!B5*ダッシュボード!B6*ダッシュボード!B7*(50000*(収益・原価!B39/収益・原価!B20))-固定費!D20*1 -> -73660000 | C17: =ダッシュボード!B5*ダッシュボード!B6*ダッシュボード!B7*(60000*(収益・原価!B39/収益・原価!B20))-固定費!D20*1 -> -71392000 | D17: =ダッシュボード!B5*ダッシュボード!B6*ダッシュボード!B7*(70000*(収益・原価!B39/収益・原価!B20))-固定費!D20*1 -> -69124000 | E17: =ダッシュボード!B5*ダッシュボード!B6*ダッシュボード!B7*(80000*(収益・原価!B39/収益・原価!B20))-固定費!D20*1 -> -66856000 | F17: =ダッシュボード!B5*ダッシュボード!B6*ダッシュボード!B7*(90000*(収益・原価!B39/収益・原価!B20))-固定費!D20*1 -> -64588000 | G17: =ダッシュボード!B5*ダッシュボード!B6*ダッシュボード!B7*(100000*(収益・原価!B39/収益・原価!B20))-固定費!D20*1 -> -62320000
A18: 1.25 | B18: =ダッシュボード!B5*ダッシュボード!B6*ダッシュボード!B7*(50000*(収益・原価!B39/収益・原価!B20))-固定費!D20*1.25 -> -94910000 | C18: =ダッシュボード!B5*ダッシュボード!B6*ダッシュボード!B7*(60000*(収益・原価!B39/収益・原価!B20))-固定費!D20*1.25 -> -92642000 | D18: =ダッシュボード!B5*ダッシュボード!B6*ダッシュボード!B7*(70000*(収益・原価!B39/収益・原価!B20))-固定費!D20*1.25 -> -90374000 | E18: =ダッシュボード!B5*ダッシュボード!B6*ダッシュボード!B7*(80000*(収益・原価!B39/収益・原価!B20))-固定費!D20*1.25 -> -88106000 | F18: =ダッシュボード!B5*ダッシュボード!B6*ダッシュボード!B7*(90000*(収益・原価!B39/収益・原価!B20))-固定費!D20*1.25 -> -85838000 | G18: =ダッシュボード!B5*ダッシュボード!B6*ダッシュボード!B7*(100000*(収益・原価!B39/収益・原価!B20))-固定費!D20*1.25 -> -83570000
A19: 1.5 | B19: =ダッシュボード!B5*ダッシュボード!B6*ダッシュボード!B7*(50000*(収益・原価!B39/収益・原価!B20))-固定費!D20*1.5 -> -116160000 | C19: =ダッシュボード!B5*ダッシュボード!B6*ダッシュボード!B7*(60000*(収益・原価!B39/収益・原価!B20))-固定費!D20*1.5 -> -113892000 | D19: =ダッシュボード!B5*ダッシュボード!B6*ダッシュボード!B7*(70000*(収益・原価!B39/収益・原価!B20))-固定費!D20*1.5 -> -111624000 | E19: =ダッシュボード!B5*ダッシュボード!B6*ダッシュボード!B7*(80000*(収益・原価!B39/収益・原価!B20))-固定費!D20*1.5 -> -109356000 | F19: =ダッシュボード!B5*ダッシュボード!B6*ダッシュボード!B7*(90000*(収益・原価!B39/収益・原価!B20))-固定費!D20*1.5 -> -107088000 | G19: =ダッシュボード!B5*ダッシュボード!B6*ダッシュボード!B7*(100000*(収益・原価!B39/収益・原価!B20))-固定費!D20*1.5 -> -104820000
