Workbook

Sheet 前提と出典
A1: KONCOCHII 損益分岐点シミュレーション — 前提と出典
A3: 【使い方】
A4: ・「損益分岐」タブの黄色セル（前提）を書き換えると、損益と分岐点、シナリオ表がすべて再計算されます。
A5: ・まず現実的な平均客単価・固定費・OTA比率を入れて、月次損益と『黒字化に必要な店舗数/件数』を見ます。
A7: 【前提の根拠】
A8: ・原価構造（店舗40%/決済3%/保険6%/システム5%）: spec 05-admin の収益内訳、および事業分析レポート(Progress)。
A9: ・粗貢献率46%・粗貢献額の例: S3h=50,000₫ のとき手残り23,000₫（=46%）はレポートの試算と一致。
A10: ・OTA成果報酬 20〜30%: レポートの留意点（Klook/KKday掲載は売上の2〜3割）。既定25%。
A11: ・KPI 1店舗5〜10件/日: spec 05・事業戦略資料。
A12: ・為替 約26,300 VND/USD (2026-07): 参考値。USD換算は目安。
A14: 【固定費は仮値（要差し替え）】
A15: ・システム/インフラ・CS人件費・店舗管理/営業・会計/保険基礎の月額は仮置き。実額が出たら黄色セルを更新。
... A23: 作成 2026-07-28 / 出典: docs/事業分析レポート・事業戦略_勝ち筋・spec/specs/05。数値は前提であり実測で更新する。

Sheet 損益分岐
A1: KONCOCHII 損益分岐点シミュレーション
A2: 黄色=入力（前提）。黒字=自動計算。通貨はVND（₫）。前提を変えると全て再計算。
A4: 為替 VND/USD（前提） | B4: 26300 | D4: 2026-07 約26,300（出典: pluang/longforecast）
A6: ① 単価と原価構造（1予約あたり）
A7: 平均客単価 ARPB（VND/予約） | B7: 70000 | D7: 資料例S3h=50,000。サイズ/プラン構成の平均で入力
A8: 店舗委託料 | B8: 0.4 | D8: 資料・05-admin
A9: 決済手数料 | B9: 0.03 | D9: 2C2P等
A10: 保険料 | B10: 0.06 | D10: 基本補償原資
A11: システム配賦 | B11: 0.05 | D11: 05-adminの収益内訳
A12: 控除合計率 | B12: =B8+B9+B10+B11 -> 0.54
A13: 粗貢献率（1−控除） | B13: =1-B12 -> 0.46
A14: 粗貢献額 /予約 | B14: =B7*B13 -> 32200
A16: ② OTA集客コスト（該当予約のみ）
A17: OTA経由の予約比率 | B17: 0.3 | D17: Klook/KKday経由の割合
A18: OTA成果報酬率（該当売上） | B18: 0.25 | D18: 一般に20〜30%
A19: 平均OTAコスト /予約 | B19: =B7*B17*B18 -> 5250
A20: 純貢献額 /予約（粗貢献−OTA） | B20: =B14-B19 -> 26950
A22: ③ 月次固定費（VND/月）
A23: システム/インフラ(Supabase/Vercel/ドメイン/2C2P固定) | B23: 8000000
A24: 多言語CS人件費 | B24: 25000000
A25: 店舗管理・営業担当 | B25: 30000000
A26: 会計・保険基礎・その他 | B26: 7000000
A27: 固定費合計 /月 | B27: =SUM(B23:B26) -> 70000000
A29: ④ 数量と損益
A30: 店舗数 | B30: 3
A31: 1店舗あたり予約/日 | B31: 7 | D31: KPI: 5〜10件
A32: 営業日/月 | B32: 30
A33: 月間予約数 | B33: =B30*B31*B32 -> 630
A34: 月間純貢献 | B34: =B33*B20 -> 16978500
A35: 月次損益（純貢献−固定費） | B35: =B34-B27 -> -53021500
A36: （参考）月次損益 USD | B36: =B35/B4 -> -2016.0266
A38: ⑤ 損益分岐（黒字化ライン）
A39: 損益分岐 月間予約数 | B39: =IF(B20<=0,"貢献≤0",CEILING(B27/B20,1)) -> 2598
A40: 損益分岐 店舗数（現在の件数/日で） | B40: =IF(B20<=0,"—",CEILING(B27/(B20*B31*B32),1)) -> 13
A41: 損益分岐 件数/日（現在の店舗数で） | B41: =IF(B20<=0,"—",CEILING(B27/(B20*B30*B32),0.1)) -> 28.9

Sheet シナリオ表
A1: 月次損益 シナリオ表（VND/月）
A2: 行=1店舗あたり予約/日、列=店舗数。前提（単価・原価・固定費）は「損益分岐」タブの値を使用。赤=赤字/緑=黒字。
A4: 予約/日 ＼ 店舗数 | B4: 3 | C4: 5 | D4: 8 | E4: 10 | F4: 15 | G4: 20
A5: 4 | B5: =3*4*損益分岐!B32*損益分岐!B20-損益分岐!B27 -> -60298000 | C5: =5*4*損益分岐!B32*損益分岐!B20-損益分岐!B27 -> -53830000 | D5: =8*4*損益分岐!B32*損益分岐!B20-損益分岐!B27 -> -44128000 | E5: =10*4*損益分岐!B32*損益分岐!B20-損益分岐!B27 -> -37660000 | F5: =15*4*損益分岐!B32*損益分岐!B20-損益分岐!B27 -> -21490000 | G5: =20*4*損益分岐!B32*損益分岐!B20-損益分岐!B27 -> -5320000
A6: 5 | B6: =3*5*損益分岐!B32*損益分岐!B20-損益分岐!B27 -> -57872500 | C6: =5*5*損益分岐!B32*損益分岐!B20-損益分岐!B27 -> -49787500 | D6: =8*5*損益分岐!B32*損益分岐!B20-損益分岐!B27 -> -37660000 | E6: =10*5*損益分岐!B32*損益分岐!B20-損益分岐!B27 -> -29575000 | F6: =15*5*損益分岐!B32*損益分岐!B20-損益分岐!B27 -> -9362500 | G6: =20*5*損益分岐!B32*損益分岐!B20-損益分岐!B27 -> 10850000
A7: 6 | B7: =3*6*損益分岐!B32*損益分岐!B20-損益分岐!B27 -> -55447000 | C7: =5*6*損益分岐!B32*損益分岐!B20-損益分岐!B27 -> -45745000 | D7: =8*6*損益分岐!B32*損益分岐!B20-損益分岐!B27 -> -31192000 | E7: =10*6*損益分岐!B32*損益分岐!B20-損益分岐!B27 -> -21490000 | F7: =15*6*損益分岐!B32*損益分岐!B20-損益分岐!B27 -> 2765000 | G7: =20*6*損益分岐!B32*損益分岐!B20-損益分岐!B27 -> 27020000
A8: 7 | B8: =3*7*損益分岐!B32*損益分岐!B20-損益分岐!B27 -> -53021500 | C8: =5*7*損益分岐!B32*損益分岐!B20-損益分岐!B27 -> -41702500 | D8: =8*7*損益分岐!B32*損益分岐!B20-損益分岐!B27 -> -24724000 | E8: =10*7*損益分岐!B32*損益分岐!B20-損益分岐!B27 -> -13405000 | F8: =15*7*損益分岐!B32*損益分岐!B20-損益分岐!B27 -> 14892500 | G8: =20*7*損益分岐!B32*損益分岐!B20-損益分岐!B27 -> 43190000
A9: 8 | B9: =3*8*損益分岐!B32*損益分岐!B20-損益分岐!B27 -> -50596000 | C9: =5*8*損益分岐!B32*損益分岐!B20-損益分岐!B27 -> -37660000 | D9: =8*8*損益分岐!B32*損益分岐!B20-損益分岐!B27 -> -18256000 | E9: =10*8*損益分岐!B32*損益分岐!B20-損益分岐!B27 -> -5320000 | F9: =15*8*損益分岐!B32*損益分岐!B20-損益分岐!B27 -> 27020000 | G9: =20*8*損益分岐!B32*損益分岐!B20-損益分岐!B27 -> 59360000
A10: 9 | B10: =3*9*損益分岐!B32*損益分岐!B20-損益分岐!B27 -> -48170500 | C10: =5*9*損益分岐!B32*損益分岐!B20-損益分岐!B27 -> -33617500 | D10: =8*9*損益分岐!B32*損益分岐!B20-損益分岐!B27 -> -11788000 | E10: =10*9*損益分岐!B32*損益分岐!B20-損益分岐!B27 -> 2765000 | F10: =15*9*損益分岐!B32*損益分岐!B20-損益分岐!B27 -> 39147500 | G10: =20*9*損益分岐!B32*損益分岐!B20-損益分岐!B27 -> 75530000
A11: 10 | B11: =3*10*損益分岐!B32*損益分岐!B20-損益分岐!B27 -> -45745000 | C11: =5*10*損益分岐!B32*損益分岐!B20-損益分岐!B27 -> -29575000 | D11: =8*10*損益分岐!B32*損益分岐!B20-損益分岐!B27 -> -5320000 | E11: =10*10*損益分岐!B32*損益分岐!B20-損益分岐!B27 -> 10850000 | F11: =15*10*損益分岐!B32*損益分岐!B20-損益分岐!B27 -> 51275000 | G11: =20*10*損益分岐!B32*損益分岐!B20-損益分岐!B27 -> 91700000
A14: 損益分岐に必要な店舗数（各 予約/日）
A15: 予約/日 | B15: 必要店舗数 | C15: 月次予約数
A16: 4 | B16: =IF(損益分岐!B20<=0,"—",CEILING(損益分岐!B27/(損益分岐!B20*4*損益分岐!B32),1)) -> 22 | C16: =IF(損益分岐!B20<=0,"—",B16*4*損益分岐!B32) -> 2640
A17: 5 | B17: =IF(損益分岐!B20<=0,"—",CEILING(損益分岐!B27/(損益分岐!B20*5*損益分岐!B32),1)) -> 18 | C17: =IF(損益分岐!B20<=0,"—",B17*5*損益分岐!B32) -> 2700
A18: 6 | B18: =IF(損益分岐!B20<=0,"—",CEILING(損益分岐!B27/(損益分岐!B20*6*損益分岐!B32),1)) -> 15 | C18: =IF(損益分岐!B20<=0,"—",B18*6*損益分岐!B32) -> 2700
A19: 7 | B19: =IF(損益分岐!B20<=0,"—",CEILING(損益分岐!B27/(損益分岐!B20*7*損益分岐!B32),1)) -> 13 | C19: =IF(損益分岐!B20<=0,"—",B19*7*損益分岐!B32) -> 2730
A20: 8 | B20: =IF(損益分岐!B20<=0,"—",CEILING(損益分岐!B27/(損益分岐!B20*8*損益分岐!B32),1)) -> 11 | C20: =IF(損益分岐!B20<=0,"—",B20*8*損益分岐!B32) -> 2640
A21: 9 | B21: =IF(損益分岐!B20<=0,"—",CEILING(損益分岐!B27/(損益分岐!B20*9*損益分岐!B32),1)) -> 10 | C21: =IF(損益分岐!B20<=0,"—",B21*9*損益分岐!B32) -> 2700
A22: 10 | B22: =IF(損益分岐!B20<=0,"—",CEILING(損益分岐!B27/(損益分岐!B20*10*損益分岐!B32),1)) -> 9 | C22: =IF(損益分岐!B20<=0,"—",B22*10*損益分岐!B32) -> 2700
